<?xml version="1.0" encoding="UTF-8" standalone="yes"?>
<?mso-application progid="Word.Document"?>
<w:wordDocument xmlns:w="http://schemas.microsoft.com/office/word/2003/wordml" xmlns:v="urn:schemas-microsoft-com:vml" xmlns:w10="urn:schemas-microsoft-com:office:word" xmlns:sl="http://schemas.microsoft.com/schemaLibrary/2003/core" xmlns:aml="http://schemas.microsoft.com/aml/2001/core" xmlns:wx="http://schemas.microsoft.com/office/word/2003/auxHint" xmlns:o="urn:schemas-microsoft-com:office:office" xmlns:dt="uuid:C2F41010-65B3-11d1-A29F-00AA00C14882" xmlns:wsp="http://schemas.microsoft.com/office/word/2003/wordml/sp2" xmlns:ns0="http://www.w3.org/2001/XMLSchema" w:macrosPresent="no" w:embeddedObjPresent="no" w:ocxPresent="no" xml:space="preserve"><w:ignoreElements w:val="http://schemas.microsoft.com/office/word/2003/wordml/sp2"/><o:DocumentProperties><o:Title>PIDS</o:Title><o:LastAuthor>Ryan D. Brooks</o:LastAuthor><o:Revision>5</o:Revision><o:TotalTime>6</o:TotalTime><o:Created>2007-04-21T17:58:00Z</o:Created><o:LastSaved>2007-04-21T18:04:00Z</o:LastSaved><o:Pages>1</o:Pages><o:Words>4</o:Words><o:Characters>50</o:Characters><o:Company>The Boeing Company</o:Company><o:Lines>1</o:Lines><o:Paragraphs>1</o:Paragraphs><o:CharactersWithSpaces>53</o:CharactersWithSpaces><o:Version>11.8125</o:Version></o:DocumentProperties><w:fonts><w:defaultFonts w:ascii="Times New Roman" w:fareast="Times New Roman" w:h-ansi="Times New Roman" w:cs="Times New Roman"/><w:font w:name="Helvetica"><w:panose-1 w:val="020B0604020202020204"/><w:charset w:val="00"/><w:family w:val="Swiss"/><w:pitch w:val="variable"/><w:sig w:usb-0="20007A87" w:usb-1="80000000" w:usb-2="00000008" w:usb-3="00000000" w:csb-0="000001FF" w:csb-1="00000000"/></w:font><w:font w:name="Tahoma"><w:panose-1 w:val="020B0604030504040204"/><w:charset w:val="00"/><w:family w:val="Swiss"/><w:pitch w:val="variable"/><w:sig w:usb-0="61007A87" w:usb-1="80000000" w:usb-2="00000008" w:usb-3="00000000" w:csb-0="000101FF" w:csb-1="00000000"/></w:font><w:font w:name="Palatino"><w:panose-1 w:val="00000000000000000000"/><w:charset w:val="00"/><w:family w:val="Roman"/><w:notTrueType/><w:pitch w:val="variable"/><w:sig w:usb-0="00000003" w:usb-1="00000000" w:usb-2="00000000" w:usb-3="00000000" w:csb-0="00000001" w:csb-1="00000000"/></w:font></w:fonts><w:lists><w:listDef w:listDefId="0"><w:lsid w:val="FFFFFF7C"/><w:plt w:val="SingleLevel"/><w:tmpl w:val="E996B4CA"/><w:lvl w:ilvl="0"><w:start w:val="1"/><w:lvlText w:val="%1."/><w:lvlJc w:val="left"/><w:pPr><w:tabs><w:tab w:val="list" w:pos="1800"/></w:tabs><w:ind w:left="1800" w:hanging="360"/></w:pPr></w:lvl></w:listDef><w:listDef w:listDefId="1"><w:lsid w:val="FFFFFF7D"/><w:plt w:val="SingleLevel"/><w:tmpl w:val="50505ECA"/><w:lvl w:ilvl="0"><w:start w:val="1"/><w:lvlText w:val="%1."/><w:lvlJc w:val="left"/><w:pPr><w:tabs><w:tab w:val="list" w:pos="1440"/></w:tabs><w:ind w:left="1440" w:hanging="360"/></w:pPr></w:lvl></w:listDef><w:listDef w:listDefId="2"><w:lsid w:val="FFFFFF7E"/><w:plt w:val="SingleLevel"/><w:tmpl w:val="BAEEE21A"/><w:lvl w:ilvl="0"><w:start w:val="1"/><w:lvlText w:val="%1."/><w:lvlJc w:val="left"/><w:pPr><w:tabs><w:tab w:val="list" w:pos="1080"/></w:tabs><w:ind w:left="1080" w:hanging="360"/></w:pPr></w:lvl></w:listDef><w:listDef w:listDefId="3"><w:lsid w:val="FFFFFF7F"/><w:plt w:val="SingleLevel"/><w:tmpl w:val="B28C17EA"/><w:lvl w:ilvl="0"><w:start w:val="1"/><w:lvlText w:val="%1."/><w:lvlJc w:val="left"/><w:pPr><w:tabs><w:tab w:val="list" w:pos="720"/></w:tabs><w:ind w:left="720" w:hanging="360"/></w:pPr></w:lvl></w:listDef><w:listDef w:listDefId="4"><w:lsid w:val="FFFFFF80"/><w:plt w:val="SingleLevel"/><w:tmpl w:val="CAE0AB78"/><w:lvl w:ilvl="0"><w:start w:val="1"/><w:nfc w:val="23"/><w:lvlText w:val=""/><w:lvlJc w:val="left"/><w:pPr><w:tabs><w:tab w:val="list" w:pos="1800"/></w:tabs><w:ind w:left="1800" w:hanging="360"/></w:pPr><w:rPr><w:rFonts w:ascii="Symbol" w:h-ansi="Symbol" w:hint="default"/></w:rPr></w:lvl></w:listDef><w:listDef w:listDefId="5"><w:lsid w:val="FFFFFF81"/><w:plt w:val="SingleLevel"/><w:tmpl w:val="FE58316C"/><w:lvl w:ilvl="0"><w:start w:val="1"/><w:nfc w:val="23"/><w:lvlText w:val=""/><w:lvlJc w:val="left"/><w:pPr><w:tabs><w:tab w:val="list" w:pos="1440"/></w:tabs><w:ind w:left="1440" w:hanging="360"/></w:pPr><w:rPr><w:rFonts w:ascii="Symbol" w:h-ansi="Symbol" w:hint="default"/></w:rPr></w:lvl></w:listDef><w:listDef w:listDefId="6"><w:lsid w:val="FFFFFF82"/><w:plt w:val="SingleLevel"/><w:tmpl w:val="1DD018C6"/><w:lvl w:ilvl="0"><w:start w:val="1"/><w:nfc w:val="23"/><w:lvlText w:val=""/><w:lvlJc w:val="left"/><w:pPr><w:tabs><w:tab w:val="list" w:pos="1080"/></w:tabs><w:ind w:left="1080" w:hanging="360"/></w:pPr><w:rPr><w:rFonts w:ascii="Symbol" w:h-ansi="Symbol" w:hint="default"/></w:rPr></w:lvl></w:listDef><w:listDef w:listDefId="7"><w:lsid w:val="FFFFFF83"/><w:plt w:val="SingleLevel"/><w:tmpl w:val="803A9086"/><w:lvl w:ilvl="0"><w:start w:val="1"/><w:nfc w:val="23"/><w:lvlText w:val=""/><w:lvlJc w:val="left"/><w:pPr><w:tabs><w:tab w:val="list" w:pos="720"/></w:tabs><w:ind w:left="720" w:hanging="360"/></w:pPr><w:rPr><w:rFonts w:ascii="Symbol" w:h-ansi="Symbol" w:hint="default"/></w:rPr></w:lvl></w:listDef><w:listDef w:listDefId="8"><w:lsid w:val="FFFFFF89"/><w:plt w:val="SingleLevel"/><w:tmpl w:val="C088BAEC"/><w:lvl w:ilvl="0"><w:start w:val="1"/><w:nfc w:val="23"/><w:lvlText w:val=""/><w:lvlJc w:val="left"/><w:pPr><w:tabs><w:tab w:val="list" w:pos="360"/></w:tabs><w:ind w:left="360" w:hanging="360"/></w:pPr><w:rPr><w:rFonts w:ascii="Symbol" w:h-ansi="Symbol" w:hint="default"/></w:rPr></w:lvl></w:listDef><w:listDef w:listDefId="9"><w:lsid w:val="087E70DB"/><w:plt w:val="SingleLevel"/><w:tmpl w:val="5BD0CBD8"/><w:lvl w:ilvl="0"><w:start w:val="1"/><w:nfc w:val="4"/><w:pStyle w:val="ListNumber"/><w:lvlText w:val="%1."/><w:lvlJc w:val="left"/><w:pPr><w:tabs><w:tab w:val="list" w:pos="1944"/></w:tabs><w:ind w:left="1944" w:hanging="720"/></w:pPr><w:rPr><w:rFonts w:hint="default"/></w:rPr></w:lvl></w:listDef><w:listDef w:listDefId="10"><w:lsid w:val="0D9B2B75"/><w:plt w:val="HybridMultilevel"/><w:tmpl w:val="7DF248D8"/><w:lvl w:ilvl="0" w:tplc="8D92823C"><w:start w:val="1"/><w:pStyle w:val="list1"/><w:lvlText w:val="%1."/><w:lvlJc w:val="left"/><w:pPr><w:tabs><w:tab w:val="list" w:pos="1080"/></w:tabs><w:ind w:left="1080" w:hanging="360"/></w:pPr><w:rPr><w:rFonts w:hint="default"/></w:rPr></w:lvl><w:lvl w:ilvl="1" w:tplc="04090019" w:tentative="on"><w:start w:val="1"/><w:nfc w:val="4"/><w:lvlText w:val="%2."/><w:lvlJc w:val="left"/><w:pPr><w:tabs><w:tab w:val="list" w:pos="1440"/></w:tabs><w:ind w:left="1440" w:hanging="360"/></w:pPr></w:lvl><w:lvl w:ilvl="2" w:tplc="0409001B" w:tentative="on"><w:start w:val="1"/><w:nfc w:val="2"/><w:lvlText w:val="%3."/><w:lvlJc w:val="right"/><w:pPr><w:tabs><w:tab w:val="list" w:pos="2160"/></w:tabs><w:ind w:left="2160" w:hanging="180"/></w:pPr></w:lvl><w:lvl w:ilvl="3" w:tplc="0409000F" w:tentative="on"><w:start w:val="1"/><w:lvlText w:val="%4."/><w:lvlJc w:val="left"/><w:pPr><w:tabs><w:tab w:val="list" w:pos="2880"/></w:tabs><w:ind w:left="2880" w:hanging="360"/></w:pPr></w:lvl><w:lvl w:ilvl="4" w:tplc="04090019" w:tentative="on"><w:start w:val="1"/><w:nfc w:val="4"/><w:lvlText w:val="%5."/><w:lvlJc w:val="left"/><w:pPr><w:tabs><w:tab w:val="list" w:pos="3600"/></w:tabs><w:ind w:left="3600" w:hanging="360"/></w:pPr></w:lvl><w:lvl w:ilvl="5" w:tplc="0409001B" w:tentative="on"><w:start w:val="1"/><w:nfc w:val="2"/><w:lvlText w:val="%6."/><w:lvlJc w:val="right"/><w:pPr><w:tabs><w:tab w:val="list" w:pos="4320"/></w:tabs><w:ind w:left="4320" w:hanging="180"/></w:pPr></w:lvl><w:lvl w:ilvl="6" w:tplc="0409000F" w:tentative="on"><w:start w:val="1"/><w:lvlText w:val="%7."/><w:lvlJc w:val="left"/><w:pPr><w:tabs><w:tab w:val="list" w:pos="5040"/></w:tabs><w:ind w:left="5040" w:hanging="360"/></w:pPr></w:lvl><w:lvl w:ilvl="7" w:tplc="04090019" w:tentative="on"><w:start w:val="1"/><w:nfc w:val="4"/><w:lvlText w:val="%8."/><w:lvlJc w:val="left"/><w:pPr><w:tabs><w:tab w:val="list" w:pos="5760"/></w:tabs><w:ind w:left="5760" w:hanging="360"/></w:pPr></w:lvl><w:lvl w:ilvl="8" w:tplc="0409001B" w:tentative="on"><w:start w:val="1"/><w:nfc w:val="2"/><w:lvlText w:val="%9."/><w:lvlJc w:val="right"/><w:pPr><w:tabs><w:tab w:val="list" w:pos="6480"/></w:tabs><w:ind w:left="6480" w:hanging="180"/></w:pPr></w:lvl></w:listDef><w:listDef w:listDefId="11"><w:lsid w:val="2080797B"/><w:plt w:val="HybridMultilevel"/><w:tmpl w:val="9176EC16"/><w:lvl w:ilvl="0" w:tplc="545CBCEA"><w:start w:val="1"/><w:nfc w:val="1"/><w:pStyle w:val="Caption"/><w:lvlText w:val="Table %1."/><w:lvlJc w:val="center"/><w:pPr><w:tabs><w:tab w:val="list" w:pos="720"/></w:tabs><w:ind w:left="0" w:first-line="0"/></w:pPr><w:rPr><w:rFonts w:hint="default"/></w:rPr></w:lvl><w:lvl w:ilvl="1" w:tplc="04090019" w:tentative="on"><w:start w:val="1"/><w:nfc w:val="4"/><w:lvlText w:val="%2."/><w:lvlJc w:val="left"/><w:pPr><w:tabs><w:tab w:val="list" w:pos="1440"/></w:tabs><w:ind w:left="1440" w:hanging="360"/></w:pPr></w:lvl><w:lvl w:ilvl="2" w:tplc="0409001B" w:tentative="on"><w:start w:val="1"/><w:nfc w:val="2"/><w:lvlText w:val="%3."/><w:lvlJc w:val="right"/><w:pPr><w:tabs><w:tab w:val="list" w:pos="2160"/></w:tabs><w:ind w:left="2160" w:hanging="180"/></w:pPr></w:lvl><w:lvl w:ilvl="3" w:tplc="0409000F" w:tentative="on"><w:start w:val="1"/><w:lvlText w:val="%4."/><w:lvlJc w:val="left"/><w:pPr><w:tabs><w:tab w:val="list" w:pos="2880"/></w:tabs><w:ind w:left="2880" w:hanging="360"/></w:pPr></w:lvl><w:lvl w:ilvl="4" w:tplc="04090019" w:tentative="on"><w:start w:val="1"/><w:nfc w:val="4"/><w:lvlText w:val="%5."/><w:lvlJc w:val="left"/><w:pPr><w:tabs><w:tab w:val="list" w:pos="3600"/></w:tabs><w:ind w:left="3600" w:hanging="360"/></w:pPr></w:lvl><w:lvl w:ilvl="5" w:tplc="0409001B" w:tentative="on"><w:start w:val="1"/><w:nfc w:val="2"/><w:lvlText w:val="%6."/><w:lvlJc w:val="right"/><w:pPr><w:tabs><w:tab w:val="list" w:pos="4320"/></w:tabs><w:ind w:left="4320" w:hanging="180"/></w:pPr></w:lvl><w:lvl w:ilvl="6" w:tplc="0409000F" w:tentative="on"><w:start w:val="1"/><w:lvlText w:val="%7."/><w:lvlJc w:val="left"/><w:pPr><w:tabs><w:tab w:val="list" w:pos="5040"/></w:tabs><w:ind w:left="5040" w:hanging="360"/></w:pPr></w:lvl><w:lvl w:ilvl="7" w:tplc="04090019" w:tentative="on"><w:start w:val="1"/><w:nfc w:val="4"/><w:lvlText w:val="%8."/><w:lvlJc w:val="left"/><w:pPr><w:tabs><w:tab w:val="list" w:pos="5760"/></w:tabs><w:ind w:left="5760" w:hanging="360"/></w:pPr></w:lvl><w:lvl w:ilvl="8" w:tplc="0409001B" w:tentative="on"><w:start w:val="1"/><w:nfc w:val="2"/><w:lvlText w:val="%9."/><w:lvlJc w:val="right"/><w:pPr><w:tabs><w:tab w:val="list" w:pos="6480"/></w:tabs><w:ind w:left="6480" w:hanging="180"/></w:pPr></w:lvl></w:listDef><w:listDef w:listDefId="12"><w:lsid w:val="2DD050A8"/><w:plt w:val="Multilevel"/><w:tmpl w:val="7FF67434"/><w:styleLink w:val="OutlineList"/><w:lvl w:ilvl="0"><w:start w:val="1"/><w:nfc w:val="4"/><w:lvlText w:val="%1)"/><w:lvlJc w:val="left"/><w:pPr><w:tabs><w:tab w:val="list" w:pos="720"/></w:tabs><w:ind w:left="720" w:hanging="360"/></w:pPr><w:rPr><w:rFonts w:hint="default"/></w:rPr></w:lvl><w:lvl w:ilvl="1"><w:start w:val="1"/><w:lvlText w:val="%2)"/><w:lvlJc w:val="left"/><w:pPr><w:tabs><w:tab w:val="list" w:pos="1080"/></w:tabs><w:ind w:left="1080" w:hanging="360"/></w:pPr><w:rPr><w:rFonts w:hint="default"/></w:rPr></w:lvl><w:lvl w:ilvl="2"><w:start w:val="1"/><w:nfc w:val="2"/><w:lvlText w:val="%3)"/><w:lvlJc w:val="left"/><w:pPr><w:tabs><w:tab w:val="list" w:pos="1440"/></w:tabs><w:ind w:left="1440" w:hanging="360"/></w:pPr><w:rPr><w:rFonts w:hint="default"/></w:rPr></w:lvl><w:lvl w:ilvl="3"><w:start w:val="1"/><w:lvlText w:val="(%4)"/><w:lvlJc w:val="left"/><w:pPr><w:tabs><w:tab w:val="list" w:pos="1800"/></w:tabs><w:ind w:left="1800" w:hanging="360"/></w:pPr><w:rPr><w:rFonts w:hint="default"/></w:rPr></w:lvl><w:lvl w:ilvl="4"><w:start w:val="1"/><w:nfc w:val="4"/><w:lvlText w:val="(%5)"/><w:lvlJc w:val="left"/><w:pPr><w:tabs><w:tab w:val="list" w:pos="2160"/></w:tabs><w:ind w:left="2160" w:hanging="360"/></w:pPr><w:rPr><w:rFonts w:hint="default"/></w:rPr></w:lvl><w:lvl w:ilvl="5"><w:start w:val="1"/><w:nfc w:val="2"/><w:lvlText w:val="(%6)"/><w:lvlJc w:val="left"/><w:pPr><w:tabs><w:tab w:val="list" w:pos="2520"/></w:tabs><w:ind w:left="2520" w:hanging="360"/></w:pPr><w:rPr><w:rFonts w:hint="default"/></w:rPr></w:lvl><w:lvl w:ilvl="6"><w:start w:val="1"/><w:lvlText w:val="%7."/><w:lvlJc w:val="left"/><w:pPr><w:tabs><w:tab w:val="list" w:pos="2880"/></w:tabs><w:ind w:left="2880" w:hanging="360"/></w:pPr><w:rPr><w:rFonts w:hint="default"/></w:rPr></w:lvl><w:lvl w:ilvl="7"><w:start w:val="1"/><w:nfc w:val="4"/><w:lvlText w:val="%8."/><w:lvlJc w:val="left"/><w:pPr><w:tabs><w:tab w:val="list" w:pos="3240"/></w:tabs><w:ind w:left="3240" w:hanging="360"/></w:pPr><w:rPr><w:rFonts w:hint="default"/></w:rPr></w:lvl><w:lvl w:ilvl="8"><w:start w:val="1"/><w:nfc w:val="2"/><w:lvlText w:val="%9."/><w:lvlJc w:val="left"/><w:pPr><w:tabs><w:tab w:val="list" w:pos="3600"/></w:tabs><w:ind w:left="3600" w:hanging="360"/></w:pPr><w:rPr><w:rFonts w:hint="default"/></w:rPr></w:lvl></w:listDef><w:listDef w:listDefId="13"><w:lsid w:val="529569FF"/><w:plt w:val="Multilevel"/><w:tmpl w:val="57C45F26"/><w:lvl w:ilvl="0"><w:start w:val="1"/><w:nfc w:val="4"/><w:pStyle w:val="lista"/><w:lvlText w:val="%1)"/><w:lvlJc w:val="left"/><w:pPr><w:tabs><w:tab w:val="list" w:pos="720"/></w:tabs><w:ind w:left="720" w:hanging="360"/></w:pPr><w:rPr><w:rFonts w:hint="default"/></w:rPr></w:lvl><w:lvl w:ilvl="1"><w:start w:val="1"/><w:lvlText w:val="%2)"/><w:lvlJc w:val="left"/><w:pPr><w:tabs><w:tab w:val="list" w:pos="1080"/></w:tabs><w:ind w:left="1080" w:hanging="360"/></w:pPr><w:rPr><w:rFonts w:hint="default"/></w:rPr></w:lvl><w:lvl w:ilvl="2"><w:start w:val="1"/><w:nfc w:val="2"/><w:lvlText w:val="%3)"/><w:lvlJc w:val="left"/><w:pPr><w:tabs><w:tab w:val="list" w:pos="1440"/></w:tabs><w:ind w:left="1440" w:hanging="360"/></w:pPr><w:rPr><w:rFonts w:hint="default"/></w:rPr></w:lvl><w:lvl w:ilvl="3"><w:start w:val="1"/><w:lvlText w:val="(%4)"/><w:lvlJc w:val="left"/><w:pPr><w:tabs><w:tab w:val="list" w:pos="1800"/></w:tabs><w:ind w:left="1800" w:hanging="360"/></w:pPr><w:rPr><w:rFonts w:hint="default"/></w:rPr></w:lvl><w:lvl w:ilvl="4"><w:start w:val="1"/><w:nfc w:val="4"/><w:lvlText w:val="(%5)"/><w:lvlJc w:val="left"/><w:pPr><w:tabs><w:tab w:val="list" w:pos="2160"/></w:tabs><w:ind w:left="2160" w:hanging="360"/></w:pPr><w:rPr><w:rFonts w:hint="default"/></w:rPr></w:lvl><w:lvl w:ilvl="5"><w:start w:val="1"/><w:nfc w:val="2"/><w:lvlText w:val="(%6)"/><w:lvlJc w:val="left"/><w:pPr><w:tabs><w:tab w:val="list" w:pos="2520"/></w:tabs><w:ind w:left="2520" w:hanging="360"/></w:pPr><w:rPr><w:rFonts w:hint="default"/></w:rPr></w:lvl><w:lvl w:ilvl="6"><w:start w:val="1"/><w:lvlText w:val="%7."/><w:lvlJc w:val="left"/><w:pPr><w:tabs><w:tab w:val="list" w:pos="2880"/></w:tabs><w:ind w:left="2880" w:hanging="360"/></w:pPr><w:rPr><w:rFonts w:hint="default"/></w:rPr></w:lvl><w:lvl w:ilvl="7"><w:start w:val="1"/><w:nfc w:val="4"/><w:lvlText w:val="%8."/><w:lvlJc w:val="left"/><w:pPr><w:tabs><w:tab w:val="list" w:pos="3240"/></w:tabs><w:ind w:left="3240" w:hanging="360"/></w:pPr><w:rPr><w:rFonts w:hint="default"/></w:rPr></w:lvl><w:lvl w:ilvl="8"><w:start w:val="1"/><w:nfc w:val="2"/><w:lvlText w:val="%9."/><w:lvlJc w:val="left"/><w:pPr><w:tabs><w:tab w:val="list" w:pos="3600"/></w:tabs><w:ind w:left="3600" w:hanging="360"/></w:pPr><w:rPr><w:rFonts w:hint="default"/></w:rPr></w:lvl></w:listDef><w:listDef w:listDefId="14"><w:lsid w:val="60CB0B90"/><w:plt w:val="Multilevel"/><w:tmpl w:val="0409001D"/><w:styleLink w:val="Outlinelist0"/><w:lvl w:ilvl="0"><w:start w:val="1"/><w:nfc w:val="4"/><w:lvlText w:val="%1)"/><w:lvlJc w:val="left"/><w:pPr><w:tabs><w:tab w:val="list" w:pos="360"/></w:tabs><w:ind w:left="360" w:hanging="360"/></w:pPr></w:lvl><w:lvl w:ilvl="1"><w:start w:val="1"/><w:lvlText w:val="%2)"/><w:lvlJc w:val="left"/><w:pPr><w:tabs><w:tab w:val="list" w:pos="720"/></w:tabs><w:ind w:left="720" w:hanging="360"/></w:pPr></w:lvl><w:lvl w:ilvl="2"><w:start w:val="1"/><w:nfc w:val="2"/><w:lvlText w:val="%3)"/><w:lvlJc w:val="left"/><w:pPr><w:tabs><w:tab w:val="list" w:pos="1080"/></w:tabs><w:ind w:left="1080" w:hanging="360"/></w:pPr></w:lvl><w:lvl w:ilvl="3"><w:start w:val="1"/><w:nfc w:val="4"/><w:lvlText w:val="(%4)"/><w:lvlJc w:val="left"/><w:pPr><w:tabs><w:tab w:val="list" w:pos="1440"/></w:tabs><w:ind w:left="1440" w:hanging="360"/></w:pPr></w:lvl><w:lvl w:ilvl="4"><w:start w:val="1"/><w:lvlText w:val="(%5)"/><w:lvlJc w:val="left"/><w:pPr><w:tabs><w:tab w:val="list" w:pos="1800"/></w:tabs><w:ind w:left="1800" w:hanging="360"/></w:pPr></w:lvl><w:lvl w:ilvl="5"><w:start w:val="1"/><w:nfc w:val="2"/><w:lvlText w:val="(%6)"/><w:lvlJc w:val="left"/><w:pPr><w:tabs><w:tab w:val="list" w:pos="2160"/></w:tabs><w:ind w:left="2160" w:hanging="360"/></w:pPr></w:lvl><w:lvl w:ilvl="6"><w:start w:val="1"/><w:lvlText w:val="%7."/><w:lvlJc w:val="left"/><w:pPr><w:tabs><w:tab w:val="list" w:pos="2520"/></w:tabs><w:ind w:left="2520" w:hanging="360"/></w:pPr></w:lvl><w:lvl w:ilvl="7"><w:start w:val="1"/><w:nfc w:val="4"/><w:lvlText w:val="%8."/><w:lvlJc w:val="left"/><w:pPr><w:tabs><w:tab w:val="list" w:pos="2880"/></w:tabs><w:ind w:left="2880" w:hanging="360"/></w:pPr></w:lvl><w:lvl w:ilvl="8"><w:start w:val="1"/><w:nfc w:val="2"/><w:lvlText w:val="%9."/><w:lvlJc w:val="left"/><w:pPr><w:tabs><w:tab w:val="list" w:pos="3240"/></w:tabs><w:ind w:left="3240" w:hanging="360"/></w:pPr></w:lvl></w:listDef><w:listDef w:listDefId="15"><w:lsid w:val="681B1731"/><w:plt w:val="Multilevel"/><w:tmpl w:val="638C7D82"/><w:styleLink w:val="CurrentList1"/><w:lvl w:ilvl="0"><w:start w:val="1"/><w:lvlText w:val="%1.0  "/><w:lvlJc w:val="left"/><w:pPr><w:tabs><w:tab w:val="list" w:pos="1170"/></w:tabs><w:ind w:left="0" w:first-line="0"/></w:pPr></w:lvl><w:lvl w:ilvl="1"><w:start w:val="1"/><w:suff w:val="Space"/><w:lvlText w:val="%1.%2  "/><w:lvlJc w:val="left"/><w:pPr><w:ind w:left="0" w:first-line="0"/></w:pPr></w:lvl><w:lvl w:ilvl="2"><w:start w:val="1"/><w:suff w:val="Space"/><w:lvlText w:val="%1.%2.%3  "/><w:lvlJc w:val="left"/><w:pPr><w:ind w:left="0" w:first-line="0"/></w:pPr></w:lvl><w:lvl w:ilvl="3"><w:start w:val="1"/><w:suff w:val="Space"/><w:lvlText w:val="%1.%2.%3.%4  "/><w:lvlJc w:val="left"/><w:pPr><w:ind w:left="0" w:first-line="0"/></w:pPr></w:lvl><w:lvl w:ilvl="4"><w:start w:val="1"/><w:suff w:val="Space"/><w:lvlText w:val="%1.%2.%3.%4.%5  "/><w:lvlJc w:val="left"/><w:pPr><w:ind w:left="0" w:first-line="0"/></w:pPr></w:lvl><w:lvl w:ilvl="5"><w:start w:val="1"/><w:suff w:val="Space"/><w:lvlText w:val="%1.%2.%3.%4.%5.%6  "/><w:lvlJc w:val="left"/><w:pPr><w:ind w:left="0" w:first-line="0"/></w:pPr></w:lvl><w:lvl w:ilvl="6"><w:start w:val="1"/><w:suff w:val="Space"/><w:lvlText w:val="%1.%2.%3.%4.%5.%6.%7  "/><w:lvlJc w:val="left"/><w:pPr><w:ind w:left="0" w:first-line="0"/></w:pPr></w:lvl><w:lvl w:ilvl="7"><w:start w:val="1"/><w:suff w:val="Space"/><w:lvlText w:val="%1.%2.%3.%4.%5.%6.%7.%8  "/><w:lvlJc w:val="left"/><w:pPr><w:ind w:left="0" w:first-line="0"/></w:pPr></w:lvl><w:lvl w:ilvl="8"><w:start w:val="1"/><w:suff w:val="Space"/><w:lvlText w:val="%1.%2.%3.%4.%5.%6.%7.%8.%9  "/><w:lvlJc w:val="left"/><w:pPr><w:ind w:left="0" w:first-line="0"/></w:pPr></w:lvl></w:listDef><w:listDef w:listDefId="16"><w:lsid w:val="688B6D0E"/><w:plt w:val="Multilevel"/><w:tmpl w:val="6CDEFB96"/><w:lvl w:ilvl="0"><w:start w:val="1"/><w:pStyle w:val="Heading1"/><w:suff w:val="Nothing"/><w:lvlText w:val="%1.0  "/><w:lvlJc w:val="left"/><w:pPr><w:ind w:left="461" w:hanging="461"/></w:pPr><w:rPr><w:rFonts w:hint="default"/></w:rPr></w:lvl><w:lvl w:ilvl="1"><w:start w:val="1"/><w:pStyle w:val="Heading2"/><w:suff w:val="Nothing"/><w:lvlText w:val="%1.%2  "/><w:lvlJc w:val="left"/><w:pPr><w:ind w:left="734" w:hanging="734"/></w:pPr><w:rPr><w:rFonts w:hint="default"/></w:rPr></w:lvl><w:lvl w:ilvl="2"><w:start w:val="1"/><w:pStyle w:val="Heading3"/><w:suff w:val="Nothing"/><w:lvlText w:val="%1.%2.%3  "/><w:lvlJc w:val="left"/><w:pPr><w:ind w:left="1516" w:hanging="1516"/></w:pPr><w:rPr><w:rFonts w:hint="default"/></w:rPr></w:lvl><w:lvl w:ilvl="3"><w:start w:val="1"/><w:pStyle w:val="Heading4"/><w:suff w:val="Nothing"/><w:lvlText w:val="%1.%2.%3.%4  "/><w:lvlJc w:val="left"/><w:pPr><w:ind w:left="1397" w:hanging="1397"/></w:pPr><w:rPr><w:rFonts w:hint="default"/></w:rPr></w:lvl><w:lvl w:ilvl="4"><w:start w:val="1"/><w:pStyle w:val="Heading5"/><w:suff w:val="Nothing"/><w:lvlText w:val="%1.%2.%3.%4.%5  "/><w:lvlJc w:val="left"/><w:pPr><w:ind w:left="1742" w:hanging="1742"/></w:pPr><w:rPr><w:rFonts w:hint="default"/></w:rPr></w:lvl><w:lvl w:ilvl="5"><w:start w:val="1"/><w:pStyle w:val="Heading6"/><w:suff w:val="Nothing"/><w:lvlText w:val="%1.%2.%3.%4.%5.%6  "/><w:lvlJc w:val="left"/><w:pPr><w:ind w:left="2074" w:hanging="2074"/></w:pPr><w:rPr><w:rFonts w:hint="default"/></w:rPr></w:lvl><w:lvl w:ilvl="6"><w:start w:val="1"/><w:pStyle w:val="Heading7"/><w:suff w:val="Nothing"/><w:lvlText w:val="%1.%2.%3.%4.%5.%6.%7  "/><w:lvlJc w:val="left"/><w:pPr><w:ind w:left="2405" w:hanging="2405"/></w:pPr><w:rPr><w:rFonts w:hint="default"/></w:rPr></w:lvl><w:lvl w:ilvl="7"><w:start w:val="1"/><w:pStyle w:val="Heading8"/><w:suff w:val="Nothing"/><w:lvlText w:val="%1.%2.%3.%4.%5.%6.%7.%8  "/><w:lvlJc w:val="left"/><w:pPr><w:ind w:left="2736" w:hanging="2736"/></w:pPr><w:rPr><w:rFonts w:hint="default"/></w:rPr></w:lvl><w:lvl w:ilvl="8"><w:start w:val="1"/><w:pStyle w:val="Heading9"/><w:suff w:val="Nothing"/><w:lvlText w:val="%1.%2.%3.%4.%5.%6.%7.%8.%9  "/><w:lvlJc w:val="left"/><w:pPr><w:ind w:left="3082" w:hanging="3082"/></w:pPr><w:rPr><w:rFonts w:hint="default"/></w:rPr></w:lvl></w:listDef><w:list w:ilfo="1"><w:ilst w:val="16"/></w:list><w:list w:ilfo="2"><w:ilst w:val="11"/></w:list><w:list w:ilfo="3"><w:ilst w:val="10"/></w:list><w:list w:ilfo="4"><w:ilst w:val="9"/></w:list><w:list w:ilfo="5"><w:ilst w:val="13"/><w:lvlOverride w:ilvl="0"><w:startOverride w:val="1"/></w:lvlOverride><w:lvlOverride w:ilvl="1"><w:startOverride w:val="1"/></w:lvlOverride><w:lvlOverride w:ilvl="2"><w:startOverride w:val="1"/></w:lvlOverride><w:lvlOverride w:ilvl="3"><w:startOverride w:val="1"/></w:lvlOverride><w:lvlOverride w:ilvl="4"><w:startOverride w:val="1"/></w:lvlOverride><w:lvlOverride w:ilvl="5"><w:startOverride w:val="1"/></w:lvlOverride><w:lvlOverride w:ilvl="6"><w:startOverride w:val="1"/></w:lvlOverride><w:lvlOverride w:ilvl="7"><w:startOverride w:val="1"/></w:lvlOverride><w:lvlOverride w:ilvl="8"><w:startOverride w:val="1"/></w:lvlOverride></w:list><w:list w:ilfo="6"><w:ilst w:val="12"/></w:list><w:list w:ilfo="7"><w:ilst w:val="14"/></w:list><w:list w:ilfo="8"><w:ilst w:val="15"/></w:list><w:list w:ilfo="9"><w:ilst w:val="8"/></w:list><w:list w:ilfo="10"><w:ilst w:val="7"/></w:list><w:list w:ilfo="11"><w:ilst w:val="6"/></w:list><w:list w:ilfo="12"><w:ilst w:val="5"/></w:list><w:list w:ilfo="13"><w:ilst w:val="4"/></w:list><w:list w:ilfo="14"><w:ilst w:val="3"/></w:list><w:list w:ilfo="15"><w:ilst w:val="2"/></w:list><w:list w:ilfo="16"><w:ilst w:val="1"/></w:list><w:list w:ilfo="17"><w:ilst w:val="0"/></w:list><w:ilfoMacAtCleanup w:val="8"/></w:lists><w:styles><w:versionOfBuiltInStylenames w:val="4"/><w:latentStyles w:defLockedState="off" w:latentStyleCount="156"/><w:style w:type="paragraph" w:default="on" w:styleId="Normal"><w:name w:val="Normal"/><w:rsid w:val="00A53204"/><w:pPr><w:jc w:val="both"/></w:pPr><w:rPr><wx:font wx:val="Times New Roman"/><w:sz w:val="22"/><w:lang w:val="EN-US" w:fareast="EN-US" w:bidi="AR-SA"/></w:rPr></w:style><w:style w:type="paragraph" w:styleId="Heading1"><w:name w:val="heading 1"/><wx:uiName wx:val="Heading 1"/><w:next w:val="Normal"/><w:rsid w:val="005251ED"/><w:pPr><w:pStyle w:val="Heading1"/><w:keepNext/><w:listPr><w:ilfo w:val="1"/></w:listPr><w:tabs><w:tab w:val="left" w:pos="864"/></w:tabs><w:spacing w:before="280" w:after="120"/><w:ind w:left="0" w:first-line="0"/><w:outlineLvl w:val="0"/></w:pPr><w:rPr><wx:font wx:val="Times New Roman"/><w:b/><w:caps/><w:noProof/><w:kern w:val="28"/><w:sz w:val="22"/><w:lang w:val="EN-US" w:fareast="EN-US" w:bidi="AR-SA"/></w:rPr></w:style><w:style w:type="paragraph" w:styleId="Heading2"><w:name w:val="heading 2"/><wx:uiName wx:val="Heading 2"/><w:next w:val="Normal"/><w:rsid w:val="005251ED"/><w:pPr><w:pStyle w:val="Heading2"/><w:keepNext/><w:listPr><w:ilvl w:val="1"/><w:ilfo w:val="1"/></w:listPr><w:tabs><w:tab w:val="left" w:pos="936"/></w:tabs><w:spacing w:before="240" w:after="120"/><w:ind w:left="0" w:first-line="0"/><w:outlineLvl w:val="1"/></w:pPr><w:rPr><wx:font wx:val="Times New Roman"/><w:b/><w:noProof/><w:sz w:val="22"/><w:lang w:val="EN-US" w:fareast="EN-US" w:bidi="AR-SA"/></w:rPr></w:style><w:style w:type="paragraph" w:styleId="Heading3"><w:name w:val="heading 3"/><wx:uiName wx:val="Heading 3"/><w:next w:val="Normal"/><w:rsid w:val="005251ED"/><w:pPr><w:pStyle w:val="Heading3"/><w:keepNext/><w:listPr><w:ilvl w:val="2"/><w:ilfo w:val="1"/></w:listPr><w:tabs><w:tab w:val="left" w:pos="864"/></w:tabs><w:spacing w:before="240" w:after="120"/><w:ind w:left="0" w:first-line="0"/><w:outlineLvl w:val="2"/></w:pPr><w:rPr><wx:font wx:val="Times New Roman"/><w:b/><w:noProof/><w:sz w:val="22"/><w:lang w:val="EN-US" w:fareast="EN-US" w:bidi="AR-SA"/></w:rPr></w:style><w:style w:type="paragraph" w:styleId="Heading4"><w:name w:val="heading 4"/><wx:uiName wx:val="Heading 4"/><w:next w:val="Normal"/><w:rsid w:val="005251ED"/><w:pPr><w:pStyle w:val="Heading4"/><w:keepNext/><w:listPr><w:ilvl w:val="3"/><w:ilfo w:val="1"/></w:listPr><w:tabs><w:tab w:val="left" w:pos="1224"/></w:tabs><w:spacing w:before="240" w:after="120"/><w:ind w:left="0" w:first-line="0"/><w:outlineLvl w:val="3"/></w:pPr><w:rPr><wx:font wx:val="Times New Roman"/><w:b/><w:noProof/><w:sz w:val="22"/><w:lang w:val="EN-US" w:fareast="EN-US" w:bidi="AR-SA"/></w:rPr></w:style><w:style w:type="paragraph" w:styleId="Heading5"><w:name w:val="heading 5"/><wx:uiName wx:val="Heading 5"/><w:next w:val="Normal"/><w:rsid w:val="005251ED"/><w:pPr><w:pStyle w:val="Heading5"/><w:listPr><w:ilvl w:val="4"/><w:ilfo w:val="1"/></w:listPr><w:tabs><w:tab w:val="left" w:pos="1368"/></w:tabs><w:spacing w:before="240" w:after="120"/><w:ind w:left="0" w:first-line="0"/><w:outlineLvl w:val="4"/></w:pPr><w:rPr><wx:font wx:val="Times New Roman"/><w:b/><w:noProof/><w:sz w:val="22"/><w:lang w:val="EN-US" w:fareast="EN-US" w:bidi="AR-SA"/></w:rPr></w:style><w:style w:type="paragraph" w:styleId="Heading6"><w:name w:val="heading 6"/><wx:uiName wx:val="Heading 6"/><w:next w:val="Normal"/><w:rsid w:val="005251ED"/><w:pPr><w:pStyle w:val="Heading6"/><w:listPr><w:ilvl w:val="5"/><w:ilfo w:val="1"/></w:listPr><w:tabs><w:tab w:val="left" w:pos="1440"/></w:tabs><w:spacing w:before="240" w:after="120"/><w:ind w:left="0" w:first-line="0"/><w:outlineLvl w:val="5"/></w:pPr><w:rPr><wx:font wx:val="Times New Roman"/><w:b/><w:noProof/><w:sz w:val="22"/><w:lang w:val="EN-US" w:fareast="EN-US" w:bidi="AR-SA"/></w:rPr></w:style><w:style w:type="paragraph" w:styleId="Heading7"><w:name w:val="heading 7"/><wx:uiName wx:val="Heading 7"/><w:next w:val="Normal"/><w:rsid w:val="005251ED"/><w:pPr><w:pStyle w:val="Heading7"/><w:listPr><w:ilvl w:val="6"/><w:ilfo w:val="1"/></w:listPr><w:tabs><w:tab w:val="left" w:pos="1584"/></w:tabs><w:spacing w:before="240" w:after="120"/><w:ind w:left="0" w:first-line="0"/><w:outlineLvl w:val="6"/></w:pPr><w:rPr><wx:font wx:val="Times New Roman"/><w:b/><w:noProof/><w:sz w:val="22"/><w:lang w:val="EN-US" w:fareast="EN-US" w:bidi="AR-SA"/></w:rPr></w:style><w:style w:type="paragraph" w:styleId="Heading8"><w:name w:val="heading 8"/><wx:uiName wx:val="Heading 8"/><w:next w:val="Normal"/><w:rsid w:val="005251ED"/><w:pPr><w:pStyle w:val="Heading8"/><w:listPr><w:ilvl w:val="7"/><w:ilfo w:val="1"/></w:listPr><w:tabs><w:tab w:val="left" w:pos="1728"/></w:tabs><w:spacing w:before="240" w:after="120"/><w:ind w:left="0" w:first-line="0"/><w:outlineLvl w:val="7"/></w:pPr><w:rPr><wx:font wx:val="Times New Roman"/><w:b/><w:noProof/><w:sz w:val="22"/><w:lang w:val="EN-US" w:fareast="EN-US" w:bidi="AR-SA"/></w:rPr></w:style><w:style w:type="paragraph" w:styleId="Heading9"><w:name w:val="heading 9"/><wx:uiName wx:val="Heading 9"/><w:next w:val="Normal"/><w:rsid w:val="005251ED"/><w:pPr><w:pStyle w:val="Heading9"/><w:listPr><w:ilvl w:val="8"/><w:ilfo w:val="1"/></w:listPr><w:tabs><w:tab w:val="left" w:pos="2016"/></w:tabs><w:spacing w:before="240" w:after="120"/><w:ind w:left="0" w:first-line="0"/><w:outlineLvl w:val="8"/></w:pPr><w:rPr><wx:font wx:val="Times New Roman"/><w:b/><w:noProof/><w:sz w:val="22"/><w:lang w:val="EN-US" w:fareast="EN-US" w:bidi="AR-SA"/></w:rPr></w:style><w:style w:type="character" w:default="on" w:styleId="DefaultParagraphFont"><w:name w:val="Default Paragraph Font"/><w:semiHidden/></w:style><w:style w:type="table" w:default="on" w:styleId="TableNormal"><w:name w:val="Normal Table"/><wx:uiName wx:val="Table Normal"/><w:semiHidden/><w:rPr><wx:font wx:val="Times New Roman"/></w:rPr><w:tblPr><w:tblInd w:w="0" w:type="dxa"/><w:tblCellMar><w:top w:w="0" w:type="dxa"/><w:left w:w="108" w:type="dxa"/><w:bottom w:w="0" w:type="dxa"/><w:right w:w="108" w:type="dxa"/></w:tblCellMar></w:tblPr></w:style><w:style w:type="list" w:default="on" w:styleId="NoList"><w:name w:val="No List"/><w:semiHidden/></w:style><w:style w:type="paragraph" w:styleId="TableofFigures"><w:name w:val="table of figures"/><wx:uiName wx:val="Table of Figures"/><w:basedOn w:val="Caption"/><w:next w:val="Normal"/><w:link w:val="CharChar"/><w:semiHidden/><w:rsid w:val="00A53204"/><w:pPr><w:pStyle w:val="TableofFigures"/><w:listPr><w:ilfo w:val="0"/></w:listPr></w:pPr><w:rPr><wx:font wx:val="Times New Roman"/><w:b w:val="off"/></w:rPr></w:style><w:style w:type="paragraph" w:styleId="TOC1"><w:name w:val="toc 1"/><wx:uiName wx:val="TOC 1"/><w:basedOn w:val="Normal"/><w:next w:val="Normal"/><w:autoRedefine/><w:semiHidden/><w:rsid w:val="00A53204"/><w:pPr><w:pStyle w:val="TOC1"/><w:spacing w:before="160" w:after="160"/></w:pPr><w:rPr><wx:font wx:val="Times New Roman"/></w:rPr></w:style><w:style w:type="character" w:styleId="CharChar"><w:name w:val="Char Char"/><w:basedOn w:val="DefaultParagraphFont"/><w:link w:val="TableofFigures"/><w:rsid w:val="005930F6"/><w:rPr><w:sz w:val="22"/><w:lang w:val="EN-US" w:fareast="EN-US" w:bidi="AR-SA"/></w:rPr></w:style><w:style w:type="paragraph" w:styleId="Caption"><w:name w:val="caption"/><wx:uiName wx:val="Caption"/><w:basedOn w:val="Normal"/><w:next w:val="Normal"/><w:semiHidden/><w:rsid w:val="00A53204"/><w:pPr><w:pStyle w:val="Caption"/><w:listPr><w:ilfo w:val="2"/></w:listPr><w:spacing w:before="120" w:after="120"/></w:pPr><w:rPr><wx:font wx:val="Times New Roman"/><w:b/></w:rPr></w:style><w:style w:type="paragraph" w:styleId="TOC2"><w:name w:val="toc 2"/><wx:uiName wx:val="TOC 2"/><w:basedOn w:val="Normal"/><w:next w:val="Normal"/><w:autoRedefine/><w:semiHidden/><w:rsid w:val="00A53204"/><w:pPr><w:pStyle w:val="TOC2"/><w:ind w:left="200"/></w:pPr><w:rPr><wx:font wx:val="Times New Roman"/></w:rPr></w:style><w:style w:type="paragraph" w:styleId="Salutation"><w:name w:val="Salutation"/><w:basedOn w:val="Normal"/><w:next w:val="Normal"/><w:rsid w:val="00A53204"/><w:pPr><w:pStyle w:val="Salutation"/><w:jc w:val="center"/></w:pPr><w:rPr><wx:font wx:val="Times New Roman"/></w:rPr></w:style><w:style w:type="paragraph" w:styleId="Title"><w:name w:val="Title"/><w:next w:val="Normal"/><w:rsid w:val="00A53204"/><w:pPr><w:pStyle w:val="Title"/><w:spacing w:before="120" w:after="60"/><w:jc w:val="center"/></w:pPr><w:rPr><wx:font wx:val="Times New Roman"/><w:b/><w:caps/><w:kern w:val="28"/><w:sz w:val="28"/><w:lang w:val="EN-US" w:fareast="EN-US" w:bidi="AR-SA"/></w:rPr></w:style><w:style w:type="paragraph" w:styleId="SignatureApproved"><w:name w:val="Signature:Approved"/><w:autoRedefine/><w:rsid w:val="00A53204"/><w:pPr><w:pStyle w:val="SignatureApproved"/><w:tabs><w:tab w:val="left" w:pos="0"/></w:tabs><w:spacing w:after="38" w:line="245" w:line-rule="at-least"/></w:pPr><w:rPr><wx:font wx:val="Times New Roman"/><w:snapToGrid w:val="off"/><w:sz w:val="22"/><w:lang w:val="EN-US" w:fareast="EN-US" w:bidi="AR-SA"/></w:rPr></w:style><w:style w:type="paragraph" w:styleId="SignaturePrepared"><w:name w:val="Signature:Prepared"/><w:autoRedefine/><w:rsid w:val="00A53204"/><w:pPr><w:pStyle w:val="SignaturePrepared"/><w:tabs><w:tab w:val="left" w:pos="0"/></w:tabs><w:spacing w:before="13" w:after="38" w:line="245" w:line-rule="at-least"/></w:pPr><w:rPr><wx:font wx:val="Times New Roman"/><w:snapToGrid w:val="off"/><w:sz w:val="22"/><w:lang w:val="EN-US" w:fareast="EN-US" w:bidi="AR-SA"/></w:rPr></w:style><w:style w:type="paragraph" w:styleId="SignatureSignature"><w:name w:val="Signature:Signature"/><w:autoRedefine/><w:rsid w:val="00A53204"/><w:pPr><w:pStyle w:val="SignatureSignature"/><w:spacing w:before="13" w:after="38" w:line="245" w:line-rule="at-least"/></w:pPr><w:rPr><wx:font wx:val="Times New Roman"/><w:snapToGrid w:val="off"/><w:sz w:val="22"/><w:lang w:val="EN-US" w:fareast="EN-US" w:bidi="AR-SA"/></w:rPr></w:style><w:style w:type="paragraph" w:styleId="Header"><w:name w:val="header"/><wx:uiName wx:val="Header"/><w:basedOn w:val="Normal"/><w:rsid w:val="00A53204"/><w:pPr><w:pStyle w:val="Header"/><w:tabs><w:tab w:val="center" w:pos="4320"/><w:tab w:val="right" w:pos="8640"/></w:tabs></w:pPr><w:rPr><wx:font wx:val="Times New Roman"/></w:rPr></w:style><w:style w:type="paragraph" w:styleId="date"><w:name w:val="date"/><w:rsid w:val="00A53204"/><w:pPr><w:pStyle w:val="date"/><w:tabs><w:tab w:val="left" w:pos="0"/><w:tab w:val="left" w:pos="1440"/><w:tab w:val="left" w:pos="2880"/><w:tab w:val="left" w:pos="4320"/></w:tabs><w:spacing w:line="220" w:line-rule="at-least"/></w:pPr><w:rPr><wx:font wx:val="Times New Roman"/><w:snapToGrid w:val="off"/><w:sz w:val="22"/><w:lang w:val="EN-US" w:fareast="EN-US" w:bidi="AR-SA"/></w:rPr></w:style><w:style w:type="paragraph" w:styleId="specno"><w:name w:val="specno"/><w:rsid w:val="00A53204"/><w:pPr><w:pStyle w:val="specno"/><w:tabs><w:tab w:val="left" w:pos="0"/><w:tab w:val="left" w:pos="1440"/><w:tab w:val="left" w:pos="2880"/><w:tab w:val="left" w:pos="4320"/></w:tabs><w:spacing w:line="220" w:line-rule="at-least"/><w:jc w:val="right"/></w:pPr><w:rPr><wx:font wx:val="Times New Roman"/><w:snapToGrid w:val="off"/><w:sz w:val="22"/><w:lang w:val="EN-US" w:fareast="EN-US" w:bidi="AR-SA"/></w:rPr></w:style><w:style w:type="character" w:styleId="PageNumber"><w:name w:val="page number"/><wx:uiName wx:val="Page Number"/><w:basedOn w:val="DefaultParagraphFont"/><w:rsid w:val="00A53204"/></w:style><w:style w:type="paragraph" w:styleId="superseding"><w:name w:val="superseding"/><w:rsid w:val="00A53204"/><w:pPr><w:pStyle w:val="superseding"/><w:tabs><w:tab w:val="left" w:pos="0"/><w:tab w:val="left" w:pos="1440"/><w:tab w:val="left" w:pos="2880"/><w:tab w:val="left" w:pos="4320"/></w:tabs><w:spacing w:before="58" w:line="220" w:line-rule="at-least"/><w:jc w:val="right"/></w:pPr><w:rPr><w:rFonts w:ascii="Palatino" w:h-ansi="Palatino"/><wx:font wx:val="Palatino"/><w:snapToGrid w:val="off"/><w:sz w:val="22"/><w:lang w:val="EN-US" w:fareast="EN-US" w:bidi="AR-SA"/></w:rPr></w:style><w:style w:type="paragraph" w:styleId="Footer"><w:name w:val="footer"/><wx:uiName wx:val="Footer"/><w:basedOn w:val="Normal"/><w:autoRedefine/><w:rsid w:val="00A53204"/><w:pPr><w:pStyle w:val="Footer"/><w:tabs><w:tab w:val="center" w:pos="4320"/><w:tab w:val="right" w:pos="8640"/></w:tabs><w:jc w:val="center"/></w:pPr><w:rPr><w:rFonts w:ascii="Helvetica" w:h-ansi="Helvetica" w:cs="Arial"/><wx:font wx:val="Helvetica"/><w:sz w:val="16"/><w:sz-cs w:val="18"/></w:rPr></w:style><w:style w:type="paragraph" w:styleId="Legend"><w:name w:val="Legend"/><w:basedOn w:val="Normal"/><w:autoRedefine/><w:rsid w:val="00A53204"/><w:pPr><w:pStyle w:val="Legend"/><w:spacing w:before="20"/></w:pPr><w:rPr><w:rFonts w:ascii="Helvetica" w:h-ansi="Helvetica" w:cs="Arial"/><wx:font wx:val="Helvetica"/><w:sz w:val="16"/></w:rPr></w:style><w:style w:type="character" w:styleId="Hyperlink"><w:name w:val="Hyperlink"/><w:basedOn w:val="DefaultParagraphFont"/><w:rsid w:val="00A53204"/><w:rPr><w:color w:val="0000FF"/><w:u w:val="single"/></w:rPr></w:style><w:style w:type="character" w:styleId="normal-h1"><w:name w:val="normal-h1"/><w:basedOn w:val="DefaultParagraphFont"/><w:rsid w:val="00A53204"/><w:rPr><w:rFonts w:ascii="Times New Roman" w:h-ansi="Times New Roman" w:cs="Times New Roman" w:hint="default"/><w:sz w:val="22"/><w:sz-cs w:val="22"/></w:rPr></w:style><w:style w:type="paragraph" w:styleId="FigureTitle"><w:name w:val="FigureTitle"/><w:basedOn w:val="Caption"/><w:next w:val="Normal"/><w:autoRedefine/><w:rsid w:val="00A53204"/><w:pPr><w:pStyle w:val="FigureTitle"/><w:listPr><w:ilfo w:val="0"/></w:listPr><w:jc w:val="center"/></w:pPr><w:rPr><wx:font wx:val="Times New Roman"/></w:rPr></w:style><w:style w:type="paragraph" w:styleId="TableTitle"><w:name w:val="TableTitle"/><w:basedOn w:val="Caption"/><w:next w:val="Normal"/><w:autoRedefine/><w:rsid w:val="00A53204"/><w:pPr><w:pStyle w:val="TableTitle"/><w:listPr><w:ilfo w:val="0"/></w:listPr><w:jc w:val="center"/></w:pPr><w:rPr><wx:font wx:val="Times New Roman"/></w:rPr></w:style><w:style w:type="character" w:styleId="SecurityGraphic"><w:name w:val="Security Graphic"/><w:basedOn w:val="DefaultParagraphFont"/><w:rsid w:val="00A53204"/></w:style><w:style w:type="character" w:styleId="SecurityHeading"><w:name w:val="Security Heading"/><w:basedOn w:val="DefaultParagraphFont"/><w:rsid w:val="00A53204"/></w:style><w:style w:type="character" w:styleId="SecurityPage"><w:name w:val="Security Page"/><w:basedOn w:val="DefaultParagraphFont"/><w:rsid w:val="00A53204"/></w:style><w:style w:type="character" w:styleId="SecurityPara"><w:name w:val="Security Para"/><w:basedOn w:val="DefaultParagraphFont"/><w:rsid w:val="00A53204"/></w:style><w:style w:type="character" w:styleId="SecurityParaEnd"><w:name w:val="Security Para End"/><w:basedOn w:val="DefaultParagraphFont"/><w:rsid w:val="00A53204"/></w:style><w:style w:type="character" w:styleId="SecurityTable"><w:name w:val="Security Table"/><w:basedOn w:val="DefaultParagraphFont"/><w:rsid w:val="00A53204"/></w:style><w:style w:type="character" w:styleId="SecurityTitle"><w:name w:val="Security Title"/><w:basedOn w:val="DefaultParagraphFont"/><w:rsid w:val="00A53204"/></w:style><w:style w:type="paragraph" w:styleId="Date0"><w:name w:val="Date"/><w:basedOn w:val="Normal"/><w:next w:val="Normal"/><w:rsid w:val="00A53204"/><w:pPr><w:pStyle w:val="Date0"/></w:pPr><w:rPr><wx:font wx:val="Times New Roman"/></w:rPr></w:style><w:style w:type="paragraph" w:styleId="Subtitle"><w:name w:val="Subtitle"/><w:basedOn w:val="Normal"/><w:rsid w:val="00A53204"/><w:pPr><w:pStyle w:val="Subtitle"/><w:spacing w:after="60"/><w:jc w:val="center"/></w:pPr><w:rPr><wx:font wx:val="Times New Roman"/><w:sz w:val="24"/></w:rPr></w:style><w:style w:type="paragraph" w:styleId="codeident"><w:name w:val="codeident"/><w:rsid w:val="00A53204"/><w:pPr><w:pStyle w:val="codeident"/><w:tabs><w:tab w:val="left" w:pos="0"/><w:tab w:val="left" w:pos="1440"/><w:tab w:val="left" w:pos="2880"/><w:tab w:val="left" w:pos="4320"/></w:tabs><w:spacing w:before="60" w:line="220" w:line-rule="at-least"/><w:jc w:val="right"/></w:pPr><w:rPr><wx:font wx:val="Times New Roman"/><w:snapToGrid w:val="off"/><w:sz w:val="22"/><w:lang w:val="EN-US" w:fareast="EN-US" w:bidi="AR-SA"/></w:rPr></w:style><w:style w:type="paragraph" w:styleId="HCellStart"><w:name w:val="HCellStart"/><w:autoRedefine/><w:rsid w:val="00A53204"/><w:pPr><w:pStyle w:val="HCellStart"/><w:spacing w:before="20"/><w:jc w:val="center"/></w:pPr><w:rPr><wx:font wx:val="Times New Roman"/><w:b/><w:lang w:val="EN-US" w:fareast="EN-US" w:bidi="AR-SA"/></w:rPr></w:style><w:style w:type="paragraph" w:styleId="CellBody"><w:name w:val="CellBody"/><w:autoRedefine/><w:rsid w:val="00A53204"/><w:pPr><w:pStyle w:val="CellBody"/><w:spacing w:before="60" w:after="60"/></w:pPr><w:rPr><wx:font wx:val="Times New Roman"/><w:lang w:val="EN-US" w:fareast="EN-US" w:bidi="AR-SA"/></w:rPr></w:style><w:style w:type="paragraph" w:styleId="HCellEnd"><w:name w:val="HCellEnd"/><w:basedOn w:val="HCellStart"/><w:next w:val="CellBody"/><w:autoRedefine/><w:rsid w:val="00A53204"/><w:pPr><w:pStyle w:val="HCellEnd"/></w:pPr><w:rPr><wx:font wx:val="Times New Roman"/></w:rPr></w:style><w:style w:type="paragraph" w:styleId="TOC3"><w:name w:val="toc 3"/><wx:uiName wx:val="TOC 3"/><w:basedOn w:val="Normal"/><w:next w:val="Normal"/><w:autoRedefine/><w:semiHidden/><w:rsid w:val="00A53204"/><w:pPr><w:pStyle w:val="TOC3"/><w:ind w:left="400"/></w:pPr><w:rPr><wx:font wx:val="Times New Roman"/></w:rPr></w:style><w:style w:type="paragraph" w:styleId="TOC4"><w:name w:val="toc 4"/><wx:uiName wx:val="TOC 4"/><w:basedOn w:val="Normal"/><w:next w:val="Normal"/><w:autoRedefine/><w:semiHidden/><w:rsid w:val="00A53204"/><w:pPr><w:pStyle w:val="TOC4"/><w:ind w:left="600"/></w:pPr><w:rPr><wx:font wx:val="Times New Roman"/></w:rPr></w:style><w:style w:type="paragraph" w:styleId="TOC5"><w:name w:val="toc 5"/><wx:uiName wx:val="TOC 5"/><w:basedOn w:val="Normal"/><w:next w:val="Normal"/><w:autoRedefine/><w:semiHidden/><w:rsid w:val="00A53204"/><w:pPr><w:pStyle w:val="TOC5"/><w:ind w:left="800"/></w:pPr><w:rPr><wx:font wx:val="Times New Roman"/></w:rPr></w:style><w:style w:type="paragraph" w:styleId="TOC6"><w:name w:val="toc 6"/><wx:uiName wx:val="TOC 6"/><w:basedOn w:val="Normal"/><w:next w:val="Normal"/><w:autoRedefine/><w:semiHidden/><w:rsid w:val="00A53204"/><w:pPr><w:pStyle w:val="TOC6"/><w:ind w:left="1000"/></w:pPr><w:rPr><wx:font wx:val="Times New Roman"/></w:rPr></w:style><w:style w:type="paragraph" w:styleId="TOC7"><w:name w:val="toc 7"/><wx:uiName wx:val="TOC 7"/><w:basedOn w:val="Normal"/><w:next w:val="Normal"/><w:autoRedefine/><w:semiHidden/><w:rsid w:val="00A53204"/><w:pPr><w:pStyle w:val="TOC7"/><w:ind w:left="1200"/></w:pPr><w:rPr><wx:font wx:val="Times New Roman"/></w:rPr></w:style><w:style w:type="paragraph" w:styleId="TOC8"><w:name w:val="toc 8"/><wx:uiName wx:val="TOC 8"/><w:basedOn w:val="Normal"/><w:next w:val="Normal"/><w:autoRedefine/><w:semiHidden/><w:rsid w:val="00A53204"/><w:pPr><w:pStyle w:val="TOC8"/><w:ind w:left="1400"/></w:pPr><w:rPr><wx:font wx:val="Times New Roman"/></w:rPr></w:style><w:style w:type="paragraph" w:styleId="TOC9"><w:name w:val="toc 9"/><wx:uiName wx:val="TOC 9"/><w:basedOn w:val="Normal"/><w:next w:val="Normal"/><w:autoRedefine/><w:semiHidden/><w:rsid w:val="00A53204"/><w:pPr><w:pStyle w:val="TOC9"/><w:ind w:left="1600"/></w:pPr><w:rPr><wx:font wx:val="Times New Roman"/></w:rPr></w:style><w:style w:type="paragraph" w:styleId="CellBodyCenter"><w:name w:val="CellBodyCenter"/><w:basedOn w:val="CellBody"/><w:rsid w:val="00A53204"/><w:pPr><w:pStyle w:val="CellBodyCenter"/><w:jc w:val="center"/></w:pPr><w:rPr><wx:font wx:val="Times New Roman"/></w:rPr></w:style><w:style w:type="paragraph" w:styleId="Notes"><w:name w:val="Notes"/><w:basedOn w:val="Title"/><w:autoRedefine/><w:rsid w:val="00A53204"/><w:pPr><w:pStyle w:val="Notes"/><w:tabs><w:tab w:val="left" w:pos="360"/><w:tab w:val="left" w:pos="720"/></w:tabs><w:ind w:left="720" w:hanging="720"/></w:pPr><w:rPr><wx:font wx:val="Times New Roman"/><w:b w:val="off"/></w:rPr></w:style><w:style w:type="paragraph" w:styleId="Lista0"><w:name w:val="List:a"/><w:basedOn w:val="Normal"/><w:rsid w:val="00A53204"/><w:pPr><w:pStyle w:val="Lista0"/><w:tabs><w:tab w:val="left" w:pos="360"/><w:tab w:val="left" w:pos="1080"/></w:tabs><w:spacing w:before="80" w:after="100" w:line="268" w:line-rule="at-least"/></w:pPr><w:rPr><wx:font wx:val="Times New Roman"/></w:rPr></w:style><w:style w:type="paragraph" w:styleId="Style1"><w:name w:val="Style1"/><w:basedOn w:val="Normal"/><w:rsid w:val="00A53204"/><w:pPr><w:pStyle w:val="Style1"/><w:tabs><w:tab w:val="left" w:pos="2520"/><w:tab w:val="left" w:pos="3960"/></w:tabs><w:spacing w:before="40" w:after="80"/><w:ind w:left="3960" w:hanging="3960"/></w:pPr><w:rPr><wx:font wx:val="Times New Roman"/><w:b/></w:rPr></w:style><w:style w:type="paragraph" w:styleId="RefDoc"><w:name w:val="RefDoc"/><w:basedOn w:val="Normal"/><w:autoRedefine/><w:rsid w:val="00A53204"/><w:pPr><w:pStyle w:val="RefDoc"/><w:tabs><w:tab w:val="left" w:pos="2520"/><w:tab w:val="left" w:pos="3960"/></w:tabs><w:spacing w:before="60" w:after="60"/><w:ind w:left="3960" w:hanging="3960"/></w:pPr><w:rPr><wx:font wx:val="Times New Roman"/></w:rPr></w:style><w:style w:type="paragraph" w:styleId="list1"><w:name w:val="list:1"/><w:rsid w:val="00A53204"/><w:pPr><w:pStyle w:val="list1"/><w:listPr><w:ilfo w:val="3"/></w:listPr><w:tabs><w:tab w:val="left" w:pos="360"/></w:tabs><w:spacing w:before="60" w:after="100"/></w:pPr><w:rPr><wx:font wx:val="Times New Roman"/><w:sz w:val="22"/><w:lang w:val="EN-US" w:fareast="EN-US" w:bidi="AR-SA"/></w:rPr></w:style><w:style w:type="paragraph" w:styleId="Note"><w:name w:val="Note"/><w:basedOn w:val="Normal"/><w:autoRedefine/><w:rsid w:val="00A53204"/><w:pPr><w:pStyle w:val="Note"/><w:tabs><w:tab w:val="left" w:pos="720"/></w:tabs><w:spacing w:before="60" w:after="60"/><w:ind w:left="1080" w:hanging="720"/></w:pPr><w:rPr><wx:font wx:val="Times New Roman"/></w:rPr></w:style><w:style w:type="paragraph" w:styleId="Acronym"><w:name w:val="Acronym"/><w:basedOn w:val="Normal"/><w:autoRedefine/><w:rsid w:val="00A53204"/><w:pPr><w:pStyle w:val="Acronym"/><w:tabs><w:tab w:val="left" w:pos="2880"/></w:tabs><w:spacing w:before="60" w:after="60"/><w:ind w:left="3600" w:hanging="2880"/></w:pPr><w:rPr><wx:font wx:val="Times New Roman"/></w:rPr></w:style><w:style w:type="paragraph" w:styleId="CellTitle"><w:name w:val="CellTitle"/><w:basedOn w:val="CellBody"/><w:autoRedefine/><w:rsid w:val="00A53204"/><w:pPr><w:pStyle w:val="CellTitle"/><w:jc w:val="center"/></w:pPr><w:rPr><wx:font wx:val="Times New Roman"/><w:b/></w:rPr></w:style><w:style w:type="paragraph" w:styleId="LegendTitle"><w:name w:val="LegendTitle"/><w:basedOn w:val="Legend"/><w:rsid w:val="00A53204"/><w:pPr><w:pStyle w:val="LegendTitle"/><w:jc w:val="center"/></w:pPr><w:rPr><wx:font wx:val="Helvetica"/><w:b/></w:rPr></w:style><w:style w:type="paragraph" w:styleId="LegendCenterd"><w:name w:val="LegendCenterd"/><w:basedOn w:val="Legend"/><w:rsid w:val="00A53204"/><w:pPr><w:pStyle w:val="LegendCenterd"/><w:jc w:val="center"/></w:pPr><w:rPr><wx:font wx:val="Helvetica"/></w:rPr></w:style><w:style w:type="paragraph" w:styleId="LegendCenterdItalic"><w:name w:val="LegendCenterdItalic"/><w:basedOn w:val="LegendCenterd"/><w:rsid w:val="00A53204"/><w:pPr><w:pStyle w:val="LegendCenterdItalic"/></w:pPr><w:rPr><wx:font wx:val="Helvetica"/><w:i/></w:rPr></w:style><w:style w:type="paragraph" w:styleId="TableofTables"><w:name w:val="Table of Tables"/><w:basedOn w:val="TableTitle"/><w:next w:val="Normal"/><w:rsid w:val="00A53204"/><w:pPr><w:pStyle w:val="TableofTables"/></w:pPr><w:rPr><wx:font wx:val="Times New Roman"/><w:b w:val="off"/></w:rPr></w:style><w:style w:type="paragraph" w:styleId="list10"><w:name w:val="list:1)"/><w:basedOn w:val="lista"/><w:rsid w:val="00A53204"/><w:pPr><w:pStyle w:val="list10"/><w:listPr><w:ilfo w:val="0"/></w:listPr></w:pPr><w:rPr><wx:font wx:val="Times New Roman"/></w:rPr></w:style><w:style w:type="paragraph" w:styleId="lista"><w:name w:val="list:a)"/><w:link w:val="listaChar"/><w:rsid w:val="00A53204"/><w:pPr><w:pStyle w:val="lista"/><w:listPr><w:ilfo w:val="5"/></w:listPr></w:pPr><w:rPr><wx:font wx:val="Times New Roman"/><w:sz w:val="22"/><w:lang w:val="EN-US" w:fareast="EN-US" w:bidi="AR-SA"/></w:rPr></w:style><w:style w:type="paragraph" w:styleId="CellTitleCenter"><w:name w:val="CellTitleCenter"/><w:basedOn w:val="CellTitle"/><w:rsid w:val="00A53204"/><w:pPr><w:pStyle w:val="CellTitleCenter"/></w:pPr><w:rPr><wx:font wx:val="Times New Roman"/></w:rPr></w:style><w:style w:type="paragraph" w:styleId="HCellBody"><w:name w:val="HCellBody"/><w:basedOn w:val="Normal"/><w:rsid w:val="00A53204"/><w:pPr><w:pStyle w:val="HCellBody"/><w:jc w:val="left"/></w:pPr><w:rPr><wx:font wx:val="Times New Roman"/><w:sz w:val="20"/></w:rPr></w:style><w:style w:type="paragraph" w:styleId="HCellBodyCenter"><w:name w:val="HCellBodyCenter"/><w:basedOn w:val="Normal"/><w:rsid w:val="00A53204"/><w:pPr><w:pStyle w:val="HCellBodyCenter"/><w:jc w:val="left"/></w:pPr><w:rPr><wx:font wx:val="Times New Roman"/><w:sz w:val="20"/></w:rPr></w:style><w:style w:type="paragraph" w:styleId="TableWithLinesRightJustify"><w:name w:val="TableWithLines:RightJustify"/><w:basedOn w:val="Normal"/><w:rsid w:val="00A53204"/><w:pPr><w:pStyle w:val="TableWithLinesRightJustify"/><w:jc w:val="left"/></w:pPr><w:rPr><wx:font wx:val="Times New Roman"/><w:sz w:val="20"/></w:rPr></w:style><w:style w:type="paragraph" w:styleId="TableWithLinesNotes"><w:name w:val="TableWithLines:Notes"/><w:basedOn w:val="Normal"/><w:rsid w:val="00A53204"/><w:pPr><w:pStyle w:val="TableWithLinesNotes"/><w:jc w:val="left"/></w:pPr><w:rPr><wx:font wx:val="Times New Roman"/><w:sz w:val="20"/></w:rPr></w:style><w:style w:type="paragraph" w:styleId="TableWithLinesLeftJustify"><w:name w:val="TableWithLines:LeftJustify"/><w:basedOn w:val="HCellEnd"/><w:rsid w:val="00A53204"/><w:pPr><w:pStyle w:val="TableWithLinesLeftJustify"/><w:jc w:val="left"/></w:pPr><w:rPr><wx:font wx:val="Times New Roman"/><w:b w:val="off"/><w:sz w:val="22"/></w:rPr></w:style><w:style w:type="paragraph" w:styleId="Ltxt"><w:name w:val="Ltxt"/><w:basedOn w:val="Normal"/><w:rsid w:val="00A53204"/><w:pPr><w:pStyle w:val="Ltxt"/></w:pPr><w:rPr><wx:font wx:val="Times New Roman"/></w:rPr></w:style><w:style w:type="paragraph" w:styleId="listaleadtab"><w:name w:val="list:a:leadtab"/><w:basedOn w:val="HCellEnd"/><w:rsid w:val="00A53204"/><w:pPr><w:pStyle w:val="listaleadtab"/><w:ind w:left="720"/><w:jc w:val="left"/></w:pPr><w:rPr><wx:font wx:val="Times New Roman"/><w:b w:val="off"/><w:sz w:val="22"/></w:rPr></w:style><w:style w:type="paragraph" w:styleId="TableWithLinesCenterJustify"><w:name w:val="TableWithLines:CenterJustify"/><w:basedOn w:val="HCellEnd"/><w:rsid w:val="00A53204"/><w:pPr><w:pStyle w:val="TableWithLinesCenterJustify"/></w:pPr><w:rPr><wx:font wx:val="Times New Roman"/><w:b w:val="off"/><w:sz w:val="22"/></w:rPr></w:style><w:style w:type="paragraph" w:styleId="TableWithoutLinesRightJustify"><w:name w:val="TableWithoutLines:RightJustify"/><w:basedOn w:val="HCellEnd"/><w:rsid w:val="00A53204"/><w:pPr><w:pStyle w:val="TableWithoutLinesRightJustify"/></w:pPr><w:rPr><wx:font wx:val="Times New Roman"/><w:b w:val="off"/><w:sz w:val="22"/></w:rPr></w:style><w:style w:type="paragraph" w:styleId="TableWithoutLinesLeftJustify"><w:name w:val="TableWithoutLines:LeftJustify"/><w:basedOn w:val="HCellEnd"/><w:rsid w:val="00A53204"/><w:pPr><w:pStyle w:val="TableWithoutLinesLeftJustify"/><w:jc w:val="left"/></w:pPr><w:rPr><wx:font wx:val="Times New Roman"/><w:b w:val="off"/><w:sz w:val="22"/></w:rPr></w:style><w:style w:type="paragraph" w:styleId="TableWithoutLinesCenterJustify"><w:name w:val="TableWithoutLines:CenterJustify"/><w:basedOn w:val="HCellEnd"/><w:rsid w:val="00A53204"/><w:pPr><w:pStyle w:val="TableWithoutLinesCenterJustify"/></w:pPr><w:rPr><w:rFonts w:ascii="Symbol" w:h-ansi="Symbol"/><wx:font wx:val="Symbol"/><w:b w:val="off"/><w:sz w:val="22"/></w:rPr></w:style><w:style w:type="paragraph" w:styleId="TableWithLineshdr"><w:name w:val="TableWithLines:hdr"/><w:basedOn w:val="Ltxt"/><w:rsid w:val="00A53204"/><w:pPr><w:pStyle w:val="TableWithLineshdr"/><w:jc w:val="center"/></w:pPr><w:rPr><wx:font wx:val="Times New Roman"/><w:b/><w:sz w:val="20"/></w:rPr></w:style><w:style w:type="paragraph" w:styleId="lista1"><w:name w:val="list:a"/><w:basedOn w:val="Lista0"/><w:rsid w:val="00A53204"/><w:pPr><w:pStyle w:val="lista1"/></w:pPr><w:rPr><wx:font wx:val="Times New Roman"/></w:rPr></w:style><w:style w:type="paragraph" w:styleId="TableWithoutLineshdr"><w:name w:val="TableWithoutLines:hdr"/><w:basedOn w:val="Ltxt"/><w:rsid w:val="00A53204"/><w:pPr><w:pStyle w:val="TableWithoutLineshdr"/></w:pPr><w:rPr><wx:font wx:val="Times New Roman"/></w:rPr></w:style><w:style w:type="paragraph" w:styleId="CenterNoSpaceAbove"><w:name w:val="CenterNoSpaceAbove"/><w:basedOn w:val="Ltxt"/><w:rsid w:val="00A53204"/><w:pPr><w:pStyle w:val="CenterNoSpaceAbove"/><w:jc w:val="center"/></w:pPr><w:rPr><wx:font wx:val="Times New Roman"/></w:rPr></w:style><w:style w:type="paragraph" w:styleId="LeftNoSpaceAbove"><w:name w:val="LeftNoSpaceAbove"/><w:basedOn w:val="list1"/><w:rsid w:val="00A53204"/><w:pPr><w:pStyle w:val="LeftNoSpaceAbove"/><w:listPr><w:ilfo w:val="0"/></w:listPr><w:tabs><w:tab w:val="clear" w:pos="360"/></w:tabs></w:pPr><w:rPr><wx:font wx:val="Times New Roman"/></w:rPr></w:style><w:style w:type="paragraph" w:styleId="DetChg"><w:name w:val="DetChg"/><w:basedOn w:val="Normal"/><w:rsid w:val="00A53204"/><w:pPr><w:pStyle w:val="DetChg"/><w:jc w:val="left"/></w:pPr><w:rPr><w:rFonts w:ascii="Arial" w:h-ansi="Arial"/><wx:font wx:val="Arial"/><w:b/><w:snapToGrid w:val="off"/></w:rPr></w:style><w:style w:type="paragraph" w:styleId="FigureTitle0"><w:name w:val="Figure Title"/><w:basedOn w:val="Caption"/><w:rsid w:val="00A53204"/><w:pPr><w:pStyle w:val="FigureTitle0"/><w:listPr><w:ilfo w:val="0"/></w:listPr></w:pPr><w:rPr><wx:font wx:val="Times New Roman"/></w:rPr></w:style><w:style w:type="paragraph" w:styleId="BalloonText"><w:name w:val="Balloon Text"/><w:basedOn w:val="Normal"/><w:semiHidden/><w:rsid w:val="00A53204"/><w:pPr><w:pStyle w:val="BalloonText"/></w:pPr><w:rPr><w:rFonts w:ascii="Tahoma" w:h-ansi="Tahoma" w:cs="Tahoma"/><wx:font wx:val="Tahoma"/><w:sz w:val="16"/><w:sz-cs w:val="16"/></w:rPr></w:style><w:style w:type="character" w:styleId="CommentReference"><w:name w:val="annotation reference"/><wx:uiName wx:val="Comment Reference"/><w:basedOn w:val="DefaultParagraphFont"/><w:semiHidden/><w:rsid w:val="00A53204"/><w:rPr><w:sz w:val="16"/><w:sz-cs w:val="16"/></w:rPr></w:style><w:style w:type="paragraph" w:styleId="CommentText"><w:name w:val="annotation text"/><wx:uiName wx:val="Comment Text"/><w:basedOn w:val="Normal"/><w:semiHidden/><w:rsid w:val="00A53204"/><w:pPr><w:pStyle w:val="CommentText"/></w:pPr><w:rPr><wx:font wx:val="Times New Roman"/><w:sz w:val="20"/></w:rPr></w:style><w:style w:type="paragraph" w:styleId="CommentSubject"><w:name w:val="annotation subject"/><wx:uiName wx:val="Comment Subject"/><w:basedOn w:val="CommentText"/><w:next w:val="CommentText"/><w:semiHidden/><w:rsid w:val="00A53204"/><w:pPr><w:pStyle w:val="CommentSubject"/></w:pPr><w:rPr><wx:font wx:val="Times New Roman"/><w:b/><w:b-cs/></w:rPr></w:style><w:style w:type="character" w:styleId="FollowedHyperlink"><w:name w:val="FollowedHyperlink"/><w:basedOn w:val="DefaultParagraphFont"/><w:rsid w:val="00A53204"/><w:rPr><w:color w:val="800080"/><w:u w:val="single"/></w:rPr></w:style><w:style w:type="table" w:styleId="TableGrid"><w:name w:val="Table Grid"/><w:basedOn w:val="TableNormal"/><w:rsid w:val="00A53204"/><w:pPr><w:jc w:val="both"/></w:pPr><w:rPr><wx:font wx:val="Times New Roman"/></w:rPr><w:tblPr><w:tblInd w:w="0" w:type="dxa"/><w:tblBorders><w:top w:val="single" w:sz="4" wx:bdrwidth="10" w:space="0" w:color="auto"/><w:left w:val="single" w:sz="4" wx:bdrwidth="10" w:space="0" w:color="auto"/><w:bottom w:val="single" w:sz="4" wx:bdrwidth="10" w:space="0" w:color="auto"/><w:right w:val="single" w:sz="4" wx:bdrwidth="10" w:space="0" w:color="auto"/><w:insideH w:val="single" w:sz="4" wx:bdrwidth="10" w:space="0" w:color="auto"/><w:insideV w:val="single" w:sz="4" wx:bdrwidth="10" w:space="0" w:color="auto"/></w:tblBorders><w:tblCellMar><w:top w:w="0" w:type="dxa"/><w:left w:w="108" w:type="dxa"/><w:bottom w:w="0" w:type="dxa"/><w:right w:w="108" w:type="dxa"/></w:tblCellMar></w:tblPr></w:style><w:style w:type="paragraph" w:styleId="ListNumber"><w:name w:val="List Number"/><w:basedOn w:val="List"/><w:rsid w:val="00A53204"/><w:pPr><w:pStyle w:val="ListNumber"/><w:listPr><w:ilfo w:val="4"/></w:listPr><w:tabs><w:tab w:val="left" w:pos="6465"/></w:tabs><w:spacing w:before="120"/><w:jc w:val="left"/></w:pPr><w:rPr><w:rFonts w:ascii="Helvetica" w:h-ansi="Helvetica"/><wx:font wx:val="Helvetica"/><w:sz w:val="24"/></w:rPr></w:style><w:style w:type="paragraph" w:styleId="List"><w:name w:val="List"/><w:basedOn w:val="Normal"/><w:rsid w:val="00A53204"/><w:pPr><w:pStyle w:val="List"/><w:ind w:left="360" w:hanging="360"/></w:pPr><w:rPr><wx:font wx:val="Times New Roman"/></w:rPr></w:style><w:style w:type="character" w:styleId="listaCharChar"><w:name w:val="list:a) Char Char"/><w:basedOn w:val="DefaultParagraphFont"/><w:link w:val="lista"/><w:rsid w:val="00AD390B"/><w:rPr><w:sz w:val="22"/><w:lang w:val="EN-US" w:fareast="EN-US" w:bidi="AR-SA"/></w:rPr></w:style><w:style w:type="paragraph" w:styleId="DocumentMap"><w:name w:val="Document Map"/><w:basedOn w:val="Normal"/><w:semiHidden/><w:rsid w:val="00A53204"/><w:pPr><w:pStyle w:val="DocumentMap"/><w:shd w:val="clear" w:color="auto" w:fill="000080"/></w:pPr><w:rPr><w:rFonts w:ascii="Tahoma" w:h-ansi="Tahoma" w:cs="Tahoma"/><wx:font wx:val="Tahoma"/><w:sz w:val="20"/></w:rPr></w:style><w:style w:type="list" w:styleId="OutlineList"><w:name w:val="OutlineList"/><w:basedOn w:val="NoList"/><w:rsid w:val="00A53204"/><w:pPr><w:listPr><w:ilfo w:val="6"/></w:listPr></w:pPr></w:style><w:style w:type="paragraph" w:styleId="MacroReq"><w:name w:val="MacroReq"/><w:basedOn w:val="RequirementText"/><w:rsid w:val="00A53204"/><w:pPr><w:pStyle w:val="MacroReq"/></w:pPr><w:rPr><wx:font wx:val="Times New Roman"/></w:rPr></w:style><w:style w:type="paragraph" w:styleId="RequirementID"><w:name w:val="Requirement ID"/><w:basedOn w:val="Heading1"/><w:rsid w:val="00A53204"/><w:pPr><w:pStyle w:val="RequirementID"/><w:listPr><w:ilfo w:val="0"/></w:listPr></w:pPr><w:rPr><wx:font wx:val="Times New Roman"/></w:rPr></w:style><w:style w:type="paragraph" w:styleId="RequirementText"><w:name w:val="Requirement Text"/><w:basedOn w:val="Normal"/><w:rsid w:val="00A53204"/><w:pPr><w:pStyle w:val="RequirementText"/></w:pPr><w:rPr><wx:font wx:val="Times New Roman"/></w:rPr></w:style><w:style w:type="paragraph" w:styleId="RequirementText0"><w:name w:val="Requirement_Text"/><w:basedOn w:val="MacroReq"/><w:rsid w:val="00A53204"/><w:pPr><w:pStyle w:val="RequirementText0"/></w:pPr><w:rPr><wx:font wx:val="Times New Roman"/></w:rPr></w:style><w:style w:type="list" w:styleId="Outlinelist0"><w:name w:val="Outlinelist"/><w:basedOn w:val="NoList"/><w:rsid w:val="00AD390B"/><w:pPr><w:listPr><w:ilfo w:val="7"/></w:listPr></w:pPr></w:style><w:style w:type="character" w:styleId="listaChar"><w:name w:val="list:a) Char"/><w:basedOn w:val="DefaultParagraphFont"/><w:link w:val="lista"/><w:rsid w:val="00A53204"/><w:rPr><w:sz w:val="22"/><w:lang w:val="EN-US" w:fareast="EN-US" w:bidi="AR-SA"/></w:rPr></w:style><w:style w:type="paragraph" w:styleId="MessageHeader"><w:name w:val="Message Header"/><w:basedOn w:val="Normal"/><w:rsid w:val="003D2D79"/><w:pPr><w:pStyle w:val="MessageHeader"/><w:pBdr><w:top w:val="single" w:sz="6" wx:bdrwidth="15" w:space="1" w:color="auto"/><w:left w:val="single" w:sz="6" wx:bdrwidth="15" w:space="1" w:color="auto"/><w:bottom w:val="single" w:sz="6" wx:bdrwidth="15" w:space="1" w:color="auto"/><w:right w:val="single" w:sz="6" wx:bdrwidth="15" w:space="1" w:color="auto"/></w:pBdr><w:shd w:val="pct-20" w:color="auto" w:fill="auto" wx:bgcolor="CCCCCC"/><w:ind w:left="1080" w:hanging="1080"/></w:pPr><w:rPr><w:rFonts w:ascii="Arial" w:h-ansi="Arial" w:cs="Arial"/><wx:font wx:val="Arial"/><w:sz w:val="24"/><w:sz-cs w:val="24"/></w:rPr></w:style><w:style w:type="list" w:styleId="CurrentList1"><w:name w:val="Current List1"/><w:rsid w:val="00BD1A72"/><w:pPr><w:listPr><w:ilfo w:val="8"/></w:listPr></w:pPr></w:style></w:styles><w:divs><w:div w:id="1512641436"><w:bodyDiv w:val="on"/><w:marLeft w:val="0"/><w:marRight w:val="0"/><w:marTop w:val="0"/><w:marBottom w:val="0"/><w:divBdr><w:top w:val="none" w:sz="0" wx:bdrwidth="0" w:space="0" w:color="auto"/><w:left w:val="none" w:sz="0" wx:bdrwidth="0" w:space="0" w:color="auto"/><w:bottom w:val="none" w:sz="0" wx:bdrwidth="0" w:space="0" w:color="auto"/><w:right w:val="none" w:sz="0" wx:bdrwidth="0" w:space="0" w:color="auto"/></w:divBdr></w:div></w:divs><w:shapeDefaults><o:shapedefaults v:ext="edit" spidmax="10242"/><o:shapelayout v:ext="edit"><o:idmap v:ext="edit" data="6"/></o:shapelayout></w:shapeDefaults><w:docPr><w:view w:val="print"/><w:zoom w:percent="100"/><w:doNotEmbedSystemFonts/><w:attachedTemplate w:val=""/><w:stylePaneFormatFilter w:val="0004"/><w:defaultTabStop w:val="720"/><w:punctuationKerning/><w:characterSpacingControl w:val="DontCompress"/><w:optimizeForBrowser/><w:validateAgainstSchema w:val="off"/><w:saveInvalidXML/><w:ignoreMixedContent w:val="off"/><w:alwaysShowPlaceholderText w:val="off"/><w:hdrShapeDefaults><o:shapedefaults v:ext="edit" spidmax="10242"/></w:hdrShapeDefaults><w:footnotePr><w:footnote w:type="separator"><w:p wsp:rsidR="009877DB" wsp:rsidRDefault="009877DB"><w:r><w:separator/></w:r></w:p></w:footnote><w:footnote w:type="continuation-separator"><w:p wsp:rsidR="009877DB" wsp:rsidRDefault="009877DB"><w:r><w:continuationSeparator/></w:r></w:p></w:footnote></w:footnotePr><w:endnotePr><w:endnote w:type="separator"><w:p wsp:rsidR="009877DB" wsp:rsidRDefault="009877DB"><w:r><w:separator/></w:r></w:p></w:endnote><w:endnote w:type="continuation-separator"><w:p wsp:rsidR="009877DB" wsp:rsidRDefault="009877DB"><w:r><w:continuationSeparator/></w:r></w:p></w:endnote></w:endnotePr><w:compat><w:breakWrappedTables/><w:snapToGridInCell/><w:wrapTextWithPunct/><w:useAsianBreakRules/><w:dontGrowAutofit/></w:compat><wsp:rsids><wsp:rsidRoot wsp:val="005930F6"/><wsp:rsid wsp:val="00031FA8"/><wsp:rsid wsp:val="001216A2"/><wsp:rsid wsp:val="0031395C"/><wsp:rsid wsp:val="00352BDC"/><wsp:rsid wsp:val="00370E65"/><wsp:rsid wsp:val="00374ACD"/><wsp:rsid wsp:val="003D2D79"/><wsp:rsid wsp:val="004C403B"/><wsp:rsid wsp:val="00514B92"/><wsp:rsid wsp:val="005251ED"/><wsp:rsid wsp:val="005456AA"/><wsp:rsid wsp:val="005930F6"/><wsp:rsid wsp:val="00596986"/><wsp:rsid wsp:val="006451DC"/><wsp:rsid wsp:val="006A0851"/><wsp:rsid wsp:val="007E37E3"/><wsp:rsid wsp:val="008E37A2"/><wsp:rsid wsp:val="009877DB"/><wsp:rsid wsp:val="009F64DC"/><wsp:rsid wsp:val="00A140CC"/><wsp:rsid wsp:val="00A53204"/><wsp:rsid wsp:val="00A67988"/><wsp:rsid wsp:val="00A83D79"/><wsp:rsid wsp:val="00AD390B"/><wsp:rsid wsp:val="00AF266B"/><wsp:rsid wsp:val="00BD1A72"/><wsp:rsid wsp:val="00BE7EB2"/><wsp:rsid wsp:val="00C21BA4"/><wsp:rsid wsp:val="00C84669"/><wsp:rsid wsp:val="00D514C2"/><wsp:rsid wsp:val="00D711EB"/><wsp:rsid wsp:val="00ED68A7"/></wsp:rsids></w:docPr><w:body><wx:sect><ns0:Artifact><w:p wsp:rsidR="00A67988" wsp:rsidRDefault="00A67988" wsp:rsidP="00A67988"><Set_Name><w:r><w:t>Default</w:t></w:r></Set_Name><Outline><HeadingAttribute><w:r><w:t>Name</w:t></w:r></HeadingAttribute><RecurseChildren><w:r><w:t>false</w:t></w:r></RecurseChildren></Outline><Attribute><Name><w:r><w:t>Word Formatted Content</w:t></w:r></Name></Attribute></w:p></ns0:Artifact><w:p wsp:rsidR="005456AA" wsp:rsidRPr="00031FA8" wsp:rsidRDefault="005456AA" wsp:rsidP="00031FA8"/><w:sectPr wsp:rsidR="005456AA" wsp:rsidRPr="00031FA8" wsp:rsidSect="00A83D79"><w:hdr w:type="even"><w:p wsp:rsidR="00E20D08" wsp:rsidRDefault="009877DB"/></w:hdr><w:pgSz w:w="12240" w:h="15840"/><w:pgMar w:top="1440" w:right="1440" w:bottom="1440" w:left="1440" w:header="720" w:footer="720" w:gutter="0"/><w:cols w:space="720"/><w:docGrid w:line-pitch="360"/></w:sectPr></wx:sect></w:body></w:wordDocument>