<?xml version="1.0" encoding="UTF-8"?>
<feature
      id="org.eclipse.osee.x.core.feature"
      label="%featureName"
      version="0.26.0.qualifier"
      provider-name="%providerName">

   <description>
      %description
   </description>

   <copyright>
      %copyright
   </copyright>

   <license url="%licenseURL">
      %license
   </license>

   <includes
         id="org.eclipse.osee.x.core.external.feature"
         version="0.0.0"/>

   <requires>
      <import plugin="org.eclipse.osgi"/>
      <import plugin="org.eclipse.osgi.services"/>
      <import plugin="org.slf4j.api"/>
      <import plugin="ch.qos.logback.classic" version="0.9.27" match="greaterOrEqual"/>
      <import plugin="org.apache.commons.codec"/>
      <import plugin="org.apache.xerces"/>
      <import plugin="javax.mail.glassfish"/>
      <import plugin="javax.servlet"/>
      <import plugin="javax.ws.rs" version="2.0.0" match="greaterOrEqual"/>
      <import plugin="com.google.guava" version="11.0.0" match="greaterOrEqual"/>
      <import plugin="org.junit" version="4.11.0" match="greaterOrEqual"/>
   </requires>

   <plugin
         id="org.eclipse.osee.logger"
         download-size="0"
         install-size="0"
         version="0.0.0"
         unpack="false"/>

   <plugin
         id="org.eclipse.osee.logger.slf4j"
         download-size="0"
         install-size="0"
         version="0.0.0"
         unpack="false"/>

   <plugin
         id="org.eclipse.osee.logback.config"
         download-size="0"
         install-size="0"
         version="0.0.0"
         fragment="true"
         unpack="false"/>

   <plugin
         id="org.eclipse.osee.framework.jdk.core"
         download-size="0"
         install-size="0"
         version="0.0.0"
         unpack="false"/>

   <plugin
         id="org.eclipse.osee.mail"
         download-size="0"
         install-size="0"
         version="0.0.0"
         unpack="false"/>

   <plugin
         id="org.eclipse.osee.event"
         download-size="0"
         install-size="0"
         version="0.0.0"
         unpack="false"/>

   <plugin
         id="org.eclipse.osee.event.osgi"
         download-size="0"
         install-size="0"
         version="0.0.0"
         unpack="false"/>

   <plugin
         id="org.eclipse.osee.framework.logging"
         download-size="0"
         install-size="0"
         version="0.0.0"
         unpack="false"/>

   <plugin
         id="org.eclipse.osee.executor.admin"
         download-size="0"
         install-size="0"
         version="0.0.0"
         unpack="false"/>

   <plugin
         id="org.eclipse.osee.console.admin"
         download-size="0"
         install-size="0"
         version="0.0.0"
         unpack="false"/>

   <plugin
         id="org.eclipse.osee.cache.admin"
         download-size="0"
         install-size="0"
         version="0.0.0"
         unpack="false"/>

   <plugin
         id="org.eclipse.osee.template.engine"
         download-size="0"
         install-size="0"
         version="0.0.0"
         unpack="false"/>

   <plugin
         id="org.eclipse.osee.jaxrs"
         download-size="0"
         install-size="0"
         version="0.0.0"
         unpack="false"/>

   <plugin
         id="org.eclipse.osee.jaxrs.server"
         download-size="0"
         install-size="0"
         version="0.0.0"
         unpack="false"/>

   <plugin
         id="org.eclipse.osee.jaxrs.client"
         download-size="0"
         install-size="0"
         version="0.0.0"
         unpack="false"/>

   <plugin
         id="org.eclipse.osee.account.admin"
         download-size="0"
         install-size="0"
         version="0.0.0"
         unpack="false"/>

   <plugin
         id="org.eclipse.osee.account.rest"
         download-size="0"
         install-size="0"
         version="0.0.0"
         unpack="false"/>

   <plugin
         id="org.eclipse.osee.account.rest.model"
         download-size="0"
         install-size="0"
         version="0.0.0"
         unpack="false"/>

   <plugin
         id="org.eclipse.osee.authentication.admin"
         download-size="0"
         install-size="0"
         version="0.0.0"
         unpack="false"/>

   <plugin
         id="org.eclipse.osee.authentication.ldap"
         download-size="0"
         install-size="0"
         version="0.0.0"
         unpack="false"/>

   <plugin
         id="org.eclipse.osee.authorization.admin"
         download-size="0"
         install-size="0"
         version="0.0.0"
         unpack="false"/>

   <plugin
         id="org.eclipse.osee.config.admin"
         download-size="0"
         install-size="0"
         version="0.0.0"
         unpack="false"/>

   <plugin
         id="org.eclipse.osee.account.rest.client"
         download-size="0"
         install-size="0"
         version="0.0.0"
         unpack="false"/>

   <plugin
         id="org.eclipse.osee.mail.api"
         download-size="0"
         install-size="0"
         version="0.0.0"
         unpack="false"/>

   <plugin
         id="org.eclipse.osee.activity.api"
         download-size="0"
         install-size="0"
         version="0.0.0"
         unpack="false"/>

   <plugin
         id="org.eclipse.osee.jdbc"
         download-size="0"
         install-size="0"
         version="0.0.0"
         unpack="false"/>

</feature>
